dash_d3cloud/WordCloud.py
dash_d3cloud/__init__.py
dash_d3cloud/_imports_.py
dash_d3cloud/dash_d3cloud.dev.js
dash_d3cloud/dash_d3cloud.min.js
dash_d3cloud/metadata.json
dash_d3cloud/package.json
dash_d3cloud-0.1.1.dist-info/LICENSE
dash_d3cloud-0.1.1.dist-info/METADATA
dash_d3cloud-0.1.1.dist-info/WHEEL
dash_d3cloud-0.1.1.dist-info/top_level.txt
dash_d3cloud-0.1.1.dist-info/RECORD
