Metadata-Version: 2.1
Name: dash-d3cloud
Version: 0.1.1
Summary: UNKNOWN
Home-page: https://github.com/trnkatomas/dash_d3cloud
Author: Tomas Trnka tomas@trnkatomas.eu
Author-email: tomas@trnkatomas.eu
License: MIT
Platform: UNKNOWN
